{
  "id": "dc-202201-ipsj-01",
  "slug_base": "dc-202201-ipsj",
  "slug_sequence": 1,
  "title": "ディープラーニングに基づく諷刺識別研究.",
  "authors": "厳帥, 田胡和哉, 松岡丈平",
  "venue": "情報処理学会第 84 回全国大会講演論文集",
  "year": 2022,
  "published_at": "2022.1",
  "pages": "741-742",
  "note": "",
  "link": "",
  "year_raw": "2022.1",
  "year_detected": true,
  "publication_class": "domestic_conference",
  "type": "conference",
  "doi": "",
  "arxiv": "",
  "project": "",
  "code_url": "",
  "data_url": "",
  "award": "",
  "bibtex": "",
  "pdf": "",
  "slides": "",
  "poster": "",
  "video": "",
  "tags": [],
  "abstract": "",
  "source_file": "国内学会.csv",
  "source_category": "domestic",
  "source_row_number": 4,
  "source_record": {
    "著者": "厳帥, 田胡和哉, 松岡丈平",
    "タイトル": "ディープラーニングに基づく諷刺識別研究.",
    "発行元、大会": "情報処理学会第 84 回全国大会講演論文集",
    "年月": "2022.1",
    "ページ等": "741-742"
  },
  "draft": false
}
